LICENSE
README.md
pyproject.toml
LogBar.egg-info/PKG-INFO
LogBar.egg-info/SOURCES.txt
LogBar.egg-info/dependency_links.txt
LogBar.egg-info/top_level.txt
logbar/__init__.py
logbar/buffer.py
logbar/columns.py
logbar/logbar.py
logbar/progress.py
logbar/terminal.py
logbar/util.py
tests/test_columns.py
tests/test_example.py
tests/test_log.py
tests/test_progress.py