Metadata-Version: 2.4
Name: LogBar
Version: 0.1.7
Summary: A unified Logger and ProgressBar util with zero dependencies.
Author-email: ModelCloud <qubitium@modelcloud.ai>
License-Expression: Apache-2.0
Project-URL: Homepage, https://github.com/ModelCloud/LogBar
Keywords: logger,logging,progressbar,progress bar,cli,terminal,lightweight,zero dependency,tqdm,tabulate
Classifier: Programming Language :: Python :: 3
Classifier: Operating System :: OS Independent
Requires-Python: >=3
License-File: LICENSE
Dynamic: license-file
